s3manifestcollectstatic/__init__.py
s3manifestcollectstatic/apps.py
s3manifestcollectstatic/management/__init__.py
s3manifestcollectstatic/management/commands/__init__.py
s3manifestcollectstatic/management/commands/s3manifestcollectstatic.py
s3manifestcollectstatic-0.3.2.dist-info/LICENSE
s3manifestcollectstatic-0.3.2.dist-info/METADATA
s3manifestcollectstatic-0.3.2.dist-info/WHEEL
s3manifestcollectstatic-0.3.2.dist-info/RECORD
