Metadata-Version: 2.1
Name: s3manifestcollectstatic
Version: 0.3.2
Summary: Optimized collectstatic for S3ManifestStaticStorage
Home-page: https://github.com/dduong42/s3manifestcollectstatic
License: MIT
Keywords: django,collectstatic,S3,manifest
Author: Daniel Dương
Author-email: daniel.duong@outlook.com
Requires-Python: >=3.6.1,<4.0.0
Classifier: Environment :: Web Environment
Classifier: Framework :: Django
Classifier: Intended Audience :: Developers
Classifier: License :: OSI Approved :: MIT License
Classifier: Programming Language :: Python
Classifier: Programming Language :: Python :: 3
Classifier: Programming Language :: Python :: 3.7
Classifier: Programming Language :: Python :: 3.8
Classifier: Programming Language :: Python :: 3.9
Classifier: Programming Language :: Python :: 3.10
Classifier: Programming Language :: Python :: 3.11
Classifier: Programming Language :: Python :: 3.6
Project-URL: Repository, https://github.com/dduong42/s3manifestcollectstatic
